oz/__init__.py
oz_cli-0.2.data/scripts/oz
oz_cli-0.2.dist-info/DESCRIPTION.rst
oz_cli-0.2.dist-info/METADATA
oz_cli-0.2.dist-info/RECORD
oz_cli-0.2.dist-info/WHEEL
oz_cli-0.2.dist-info/metadata.json
oz_cli-0.2.dist-info/top_level.txt
