Metadata-Version: 2.0
Name: oz-cli
Version: 0.2
Summary: Swiftly execute complex commands in the shell
Home-page: https://github.com/shaneleonard/oz
Author: Shane Leonard
Author-email: shane.william.leonard@gmail.com
License: MIT
Platform: UNKNOWN
